MANIFEST.in
setup.cfg
setup.py
src/etcd/__init__.py
src/etcd/adapter.py
src/etcd/async_client.py
src/etcd/client.py
src/etcd/response.py
src/py_etcd.egg-info/PKG-INFO
src/py_etcd.egg-info/SOURCES.txt
src/py_etcd.egg-info/dependency_links.txt
src/py_etcd.egg-info/requires.txt
src/py_etcd.egg-info/top_level.txt