Metadata-Version: 1.0
Name: py-etcd
Version: 0.1.4
Summary: Full fledged etcd-client for python. Batteries included
Home-page: UNKNOWN
Author: UNKNOWN
Author-email: UNKNOWN
License: UNKNOWN
Platform: UNKNOWN
